cgsubmit/__init__.py
cgsubmit/__main__.py
cgsubmit/api/__init__.py
cgsubmit/api/api.py
cgsubmit/games/__init__.py
cgsubmit/games/games.py
cgsubmit-1.2.2.dist-info/LICENSE
cgsubmit-1.2.2.dist-info/METADATA
cgsubmit-1.2.2.dist-info/WHEEL
cgsubmit-1.2.2.dist-info/top_level.txt
cgsubmit-1.2.2.dist-info/RECORD
