Metadata-Version: 2.1
Name: cgsubmit
Version: 1.2.2
Summary: Analyse your submit in codingame competitions.
Author-email: FrequentlyMissedDeadlines <FrequentlyMissedDeadlines+cgsubmit@gmail.com>
Project-URL: Homepage, https://github.com/FrequentlyMissedDeadlines/cgsubmit
Project-URL: Bug Reports, https://github.com/FrequentlyMissedDeadlines/cgsubmit/issues
Project-URL: Source, https://github.com/FrequentlyMissedDeadlines/cgsubmit
Keywords: CodinGame
Classifier: Programming Language :: Python :: 3
Classifier: License :: OSI Approved :: MIT License
Classifier: Operating System :: OS Independent
Classifier: Development Status :: 5 - Production/Stable
Classifier: Intended Audience :: End Users/Desktop
Classifier: Natural Language :: English
Classifier: Topic :: Software Development
Classifier: Programming Language :: Python :: 3.7
Classifier: Programming Language :: Python :: 3.8
Classifier: Programming Language :: Python :: 3.9
Classifier: Programming Language :: Python :: 3.10
Classifier: Programming Language :: Python :: 3.11
Requires-Python: >=3.7
License-File: LICENSE
Requires-Dist: requests
